qtoggleserver/thingspeak/__init__.py
qtoggleserver/thingspeak/exceptions.py
qtoggleserver/thingspeak/thingspeak.py
qtoggleserver_thingspeak-1.3.0.dist-info/licenses/LICENSE.txt
qtoggleserver_thingspeak-1.3.0.dist-info/METADATA
qtoggleserver_thingspeak-1.3.0.dist-info/WHEEL
qtoggleserver_thingspeak-1.3.0.dist-info/top_level.txt
qtoggleserver_thingspeak-1.3.0.dist-info/RECORD
