Metadata-Version: 2.4
Name: qtoggleserver-thingspeak
Version: 1.3.0
Summary: Send values from qToggleServer to ThingSpeak
Author-email: Calin Crisan <ccrisan@gmail.com>
License: Apache 2.0
Requires-Python: >=3.11
License-File: LICENSE.txt
Requires-Dist: aiohttp
Dynamic: license-file
